{"title":"The.First.48.S11E33.720p.HDTV.x264-MOMENTUM","uid":6614335,"size":986205001,"categoryP":"video","categoryS":"hd___tv_shows","magnet":"?xt=urn:btih:04b7324ecaade458af28214eb25d532b318b6b77&amp;dn=The.First.48.S11E33.720p.HDTV.x264-MOMENTUM&amp;tr=udp%3A%2F%2Ftracker.openbittorrent.com%3A80&amp;tr=udp%3A%2F%2Fopen.demonii.com%3A1337&amp;tr=udp%3A%2F%2Ftracker.coppersurfer.tk%3A6969&amp;tr=udp%3A%2F%2Fexodus.desync.com%3A6969","seeders":1,"leechers":0,"uploader":"sceneline","files":26,"time":1313727998,"description":"- &lt;a href=&quot;\nhttp://www.Speed.Cd&quot; rel=&quot;nofollow&quot; target=&quot;_NEW&quot;&gt;\nhttp://www.Speed.Cd&lt;/a&gt;\n &lt;a href=&quot;\nhttp://www.Speed.Cd&quot; rel=&quot;nofollow&quot; target=&quot;_NEW&quot;&gt;\nhttp://www.Speed.Cd&lt;/a&gt;      fast  and The Hottest Private Tracker on the net\n\n(((--submit for invite!!--)))\n\nPlease Seed back to make the speed Faster!!!\n\nand don't forget to visit .......http://www.Speed.Cd  ......\n\n\n ............ NFO .............\n-The.First.48.S11E33.720p.HDTV.x264-MOMENTUM\n\nEpisode Title....: Last Words/Nowhere to Hide\nRelease Date.....: 2011-08-19\nFilesize.........: 923.392MB\nRuntime..........: 44m0s\nVideo............: 2492Kbps x264\nAudio............: 384Kbps AC3 2 channels\nFrame Size.......: 1276x718\nFrame Rate.......: 29.970 fps\n\nRelease Notes....: 200th EPISODE!!","torrent":{"xt":"urn:btih:04b7324ecaade458af28214eb25d532b318b6b77","amp;dn":"The.First.48.S11E33.720p.HDTV.x264-MOMENTUM","amp;tr":["udp%3A%2F%2Ftracker.openbittorrent.com%3A80","udp%3A%2F%2Fopen.demonii.com%3A1337","udp%3A%2F%2Ftracker.coppersurfer.tk%3A6969","udp%3A%2F%2Fexodus.desync.com%3A6969"],"infoHash":"04b7324ecaade458af28214eb25d532b318b6b77","infoHashBuffer":{"type":"Buffer","data":[4,183,50,78,202,173,228,88,175,40,33,78,178,93,83,43,49,139,107,119]},"announce":[],"urlList":[]}}