{"title":"Danielle Dax - Blast The Human Flower","uid":4791617,"size":106319548,"categoryP":"audio","categoryS":"music","magnet":"?xt=urn:btih:05026f4da0fa9189a64059882d8484b5c15b67ed&amp;dn=Danielle+Dax+-+Blast+The+Human+Flower&amp;tr=udp%3A%2F%2Ftracker.openbittorrent.com%3A80&amp;tr=udp%3A%2F%2Fopen.demonii.com%3A1337&amp;tr=udp%3A%2F%2Ftracker.coppersurfer.tk%3A6969&amp;tr=udp%3A%2F%2Fexodus.desync.com%3A6969","seeders":1,"leechers":0,"uploader":"12X21","files":11,"time":1237739383,"description":"Danielle Dax - Blast The Human Flower:\nMP3\nCBR\n320 BitRate","torrent":{"xt":"urn:btih:05026f4da0fa9189a64059882d8484b5c15b67ed","amp;dn":"Danielle+Dax+-+Blast+The+Human+Flower","amp;tr":["udp%3A%2F%2Ftracker.openbittorrent.com%3A80","udp%3A%2F%2Fopen.demonii.com%3A1337","udp%3A%2F%2Ftracker.coppersurfer.tk%3A6969","udp%3A%2F%2Fexodus.desync.com%3A6969"],"infoHash":"05026f4da0fa9189a64059882d8484b5c15b67ed","infoHashBuffer":{"type":"Buffer","data":[5,2,111,77,160,250,145,137,166,64,89,136,45,132,132,181,193,91,103,237]},"announce":[],"urlList":[]}}