{"title":"2x1 hentai lolimaxxx","uid":10119741,"size":165532117,"categoryP":"porn","categoryS":"other","magnet":"?xt=urn:btih:09c0d672165e28733122c1174db1aaff4ddb4474&amp;dn=2x1+hentai+lolimaxxx&amp;tr=udp%3A%2F%2Ftracker.openbittorrent.com%3A80&amp;tr=udp%3A%2F%2Fopen.demonii.com%3A1337&amp;tr=udp%3A%2F%2Ftracker.coppersurfer.tk%3A6969&amp;tr=udp%3A%2F%2Fexodus.desync.com%3A6969","seeders":1,"leechers":0,"uploader":"kiranary","files":1,"time":1399654230,"description":"2x1 hentai lolimaxxx","torrent":{"xt":"urn:btih:09c0d672165e28733122c1174db1aaff4ddb4474","amp;dn":"2x1+hentai+lolimaxxx","amp;tr":["udp%3A%2F%2Ftracker.openbittorrent.com%3A80","udp%3A%2F%2Fopen.demonii.com%3A1337","udp%3A%2F%2Ftracker.coppersurfer.tk%3A6969","udp%3A%2F%2Fexodus.desync.com%3A6969"],"infoHash":"09c0d672165e28733122c1174db1aaff4ddb4474","infoHashBuffer":{"type":"Buffer","data":[9,192,214,114,22,94,40,115,49,34,193,23,77,177,170,255,77,219,68,116]},"announce":[],"urlList":[]}}