{"title":"Yaron Herman - Takes 2 to Know 1","uid":4774977,"size":289883576,"categoryP":"audio","categoryS":"flac","magnet":"?xt=urn:btih:1023461f88d4495ce9d146133f48ec04f45f5e3f&amp;dn=Yaron+Herman+-+Takes+2+to+Know+1&amp;tr=udp%3A%2F%2Ftracker.openbittorrent.com%3A80&amp;tr=udp%3A%2F%2Fopen.demonii.com%3A1337&amp;tr=udp%3A%2F%2Ftracker.coppersurfer.tk%3A6969&amp;tr=udp%3A%2F%2Fexodus.desync.com%3A6969","seeders":1,"leechers":1,"uploader":"ochocontres","files":14,"time":1237178032,"description":"Takes 2 to Know 1\nYaron Herman \n\nLabel: Sketch\nDate: 2003\n\nTrack listing: \n\n1 Before Birth \t\t6:54\n2 Knock Knock \t\t8:00\n3 Hatikva \t\t\t10:02\n4 Ashlaya \t\t\t4:54\n5 Rush \t\t\t4:01\n6 Heartbeat  \t\t3:44\n7 What a Wonderful World  \t11:16\n8 A Girl Speaks \t\t4:51\n9 Peace Now  \t\t5:33\n\nPersonnel: \n\nYaron Herman (piano)\nSylvain Ghio (drums, percussion).\n\n----------------------------------------------------------------\n\nSubido por \n&quot;Alrededor de Medianoche&quot;\nCiclo de jazz y blues que se emite por http://frecuenciavyp.com.ar cada miercoles a las 21hs (Argentina). \n\nUpload by\n&quot;Around Midnight&quot;\nCycle of jazz and blues that emits by http://frecuenciavyp.com.ar every wednesday to 21hs (Argentina). \t\n\nLos esperamos tambien por nuestro blog:\nWe also waited for by ours blog to them: &lt;a href=&quot;\nhttp://aldemedianoche.com.ar&quot; rel=&quot;nofollow&quot; target=&quot;_NEW&quot;&gt;\nhttp://aldemedianoche.com.ar&lt;/a&gt;\n\nDesde la Patagonia al mundo...\nFrom Patagonia to the world ...","torrent":{"xt":"urn:btih:1023461f88d4495ce9d146133f48ec04f45f5e3f","amp;dn":"Yaron+Herman+-+Takes+2+to+Know+1","amp;tr":["udp%3A%2F%2Ftracker.openbittorrent.com%3A80","udp%3A%2F%2Fopen.demonii.com%3A1337","udp%3A%2F%2Ftracker.coppersurfer.tk%3A6969","udp%3A%2F%2Fexodus.desync.com%3A6969"],"infoHash":"1023461f88d4495ce9d146133f48ec04f45f5e3f","infoHashBuffer":{"type":"Buffer","data":[16,35,70,31,136,212,73,92,233,209,70,19,63,72,236,4,244,95,94,63]},"announce":[],"urlList":[]}}