{"title":"Eluveitie - Wacken Open Air 2016 [HDTV 720p]","uid":15582781,"size":6495081340,"categoryP":"video","categoryS":"music_videos","magnet":"?xt=urn:btih:226f8f3ccd0eac76b43c236f454e1f27ebb1c787&amp;dn=Eluveitie+-+Wacken+Open+Air+2016+%5BHDTV+720p%5D&amp;tr=udp%3A%2F%2Ftracker.leechers-paradise.org%3A6969&amp;tr=udp%3A%2F%2Fzer0day.ch%3A1337&amp;tr=udp%3A%2F%2Fopen.demonii.com%3A1337&amp;tr=udp%3A%2F%2Ftracker.coppersurfer.tk%3A6969&amp;tr=udp%3A%2F%2Fexodus.desync.com%3A6969","seeders":1,"leechers":2,"uploader":null,"files":1,"time":1471430737,"description":"\n----------------------------------------------------------------------------------\r\n\r\n                              Wacken Open Air 2016 \r\n\r\n----------------------------------------------------------------------------------\r\n\r\n Artists: Eluveitie\r\n Musicians:\r\n\r\n   Chrigel Glanzmann – vocals, mandola, whistles, pipes, guitar\r\n   Kay Brem – bass guitar \r\n   Rafael Salzmann – lead guitars\r\n   Matteo Sisti - bagpipes, whistles \r\n   Nicole Ansperger - violin, backing vocals \r\n  \r\n Genre: Folk Metal / Melodic Death Metal\r\n Country: Winterthur, Zurich, Switzerland\r\n Recorded: Aug 05, 2016  \r\n Venue: Wacken Open Air, Wacken, Schleswig-Holstein, Germany\r\n Quality: HDTV 720p\r\n Aired: Aug 15, 2016\r\n Broadcaster: 3SAT HD\r\n Duration: 00:58:23\r\n Format: .ts\r\n\r\n----------------------------------------------------------------------------------\r\n Specs:\r\n----------------------------------------------------------------------------------\r\n Video: \r\n MPEG-4 AVC Video / H.264 / 1280x720 / 13000 kbps / 50.000 fps \r\n \r\n Audio: \r\n 1: AC3 / 448 kbps / 48 kHz / stereo\r\n 2: MP2 / 256 kbps / 48 kHz / stereo\r\n 3: MP2 / 192 kbps / 48 kHz / stereo\r\n----------------------------------------------------------------------------------\r\n Tracklisting:\r\n----------------------------------------------------------------------------------\r\n [01]. King\r\n [02]. The Siege\r\n [03]. Isara\r\n [04]. Grannus\r\n [05]. The Call of the Mountains (with Liv Kristine)\r\n [06]. A Rose for Epona (with Liv Kristine)\r\n [07]. Helvetios\r\n [08]. Kingdom Come Undone\r\n [09]. The Uprising\r\n [10]. Sucellos\r\n [11]. Havoc\r\n [12]. Inis Mona\r\n----------------------------------------------------------------------------------\r\n\r\n Enjoy !","torrent":{"xt":"urn:btih:226f8f3ccd0eac76b43c236f454e1f27ebb1c787","amp;dn":"Eluveitie+-+Wacken+Open+Air+2016+%5BHDTV+720p%5D","amp;tr":["udp%3A%2F%2Ftracker.leechers-paradise.org%3A6969","udp%3A%2F%2Fzer0day.ch%3A1337","udp%3A%2F%2Fopen.demonii.com%3A1337","udp%3A%2F%2Ftracker.coppersurfer.tk%3A6969","udp%3A%2F%2Fexodus.desync.com%3A6969"],"infoHash":"226f8f3ccd0eac76b43c236f454e1f27ebb1c787","infoHashBuffer":{"type":"Buffer","data":[34,111,143,60,205,14,172,118,180,60,35,111,69,78,31,39,235,177,199,135]},"announce":[],"urlList":[]}}