{"title":"Dyro feat. Ryder - Calling Out (Original Mix) [Revealed Recordin","uid":9802050,"size":10912776,"categoryP":"audio","categoryS":"music","magnet":"?xt=urn:btih:30382f19e3a0fd9ff34abf4588665f7b7b2c4c76&amp;dn=Dyro+feat.+Ryder+-+Calling+Out+%28Original+Mix%29+%5BRevealed+Recordin&amp;tr=udp%3A%2F%2Ftracker.openbittorrent.com%3A80&amp;tr=udp%3A%2F%2Fopen.demonii.com%3A1337&amp;tr=udp%3A%2F%2Ftracker.coppersurfer.tk%3A6969&amp;tr=udp%3A%2F%2Fexodus.desync.com%3A6969","seeders":1,"leechers":0,"uploader":"Aevon","files":-1,"time":1395396275,"description":"Dyro feat. Ryder - Calling Out (Original Mix)\n\nGeneral\n\nFormat : MPEG Audio\nFile size : 10.47 MiB\nDuration : 4mn 31s\nOverall bit rate mode : Constant\nOverall bit rate : 320 Kbps\nAlbum : Calling Out (Original Mix) - Single\nAlbum/Performer : Dyro feat. Ryder\nPart/Position : 1\nPart/Total : 1\nTrack name : Calling Out (Original Mix)\nTrack name/Position : 01\nTrack name/Total : 01\nGenre : Electro House \nWriting library : LAME3.99.5\nCover Art : Yes\nCover Type : image/png\nRecord Label : Revealed Recordings\n\nComment below in the comment section for any EDM songs, etc requests and I Will try to upload it.\n\nPlease Rate,Comment and SEED.\n\nIf you like this Torrent please take a second to comment Thank You in below in the comment section.","torrent":{"xt":"urn:btih:30382f19e3a0fd9ff34abf4588665f7b7b2c4c76","amp;dn":"Dyro+feat.+Ryder+-+Calling+Out+%28Original+Mix%29+%5BRevealed+Recordin","amp;tr":["udp%3A%2F%2Ftracker.openbittorrent.com%3A80","udp%3A%2F%2Fopen.demonii.com%3A1337","udp%3A%2F%2Ftracker.coppersurfer.tk%3A6969","udp%3A%2F%2Fexodus.desync.com%3A6969"],"infoHash":"30382f19e3a0fd9ff34abf4588665f7b7b2c4c76","infoHashBuffer":{"type":"Buffer","data":[48,56,47,25,227,160,253,159,243,74,191,69,136,102,95,123,123,44,76,118]},"announce":[],"urlList":[]}}