{"title":"Requested - WA-3324 Sasha Sparks, Christina Carter, Sandra Romai","uid":6987332,"size":237014212,"categoryP":"porn","categoryS":"movie_clips","magnet":"?xt=urn:btih:4ae89c8e7b26096110f25adffdbe6a05ac396ae3&amp;dn=Requested+-+WA-3324+Sasha+Sparks%2C+Christina+Carter%2C+Sandra+Romai&amp;tr=udp%3A%2F%2Ftracker.openbittorrent.com%3A80&amp;tr=udp%3A%2F%2Fopen.demonii.com%3A1337&amp;tr=udp%3A%2F%2Ftracker.coppersurfer.tk%3A6969&amp;tr=udp%3A%2F%2Fexodus.desync.com%3A6969","seeders":1,"leechers":0,"uploader":"shallow2","files":-1,"time":1327609934,"description":"Requested by @rebel18\n\nSasha Sparks, Christina Carter, Sandra Romain Dec 23, 2005\n\nChristina and Sasha both feel the wrath of Sandra's domination. They are tied to a chandelier by their wrists, punished and humiliated. Then, dressed in latex, they are forced to pleasure each other. Finally, Sandra fucks them in the ass and pussy with a strap-on.\n &lt;a href=&quot;\nhttp://www.whippedass.com/site/shoot.jsp?shootId=3324&quot; rel=&quot;nofollow&quot; target=&quot;_NEW&quot;&gt;\nhttp://www.whippedass.com/site/shoot.jsp?shootId=3324&lt;/a&gt;","torrent":{"xt":"urn:btih:4ae89c8e7b26096110f25adffdbe6a05ac396ae3","amp;dn":"Requested+-+WA-3324+Sasha+Sparks%2C+Christina+Carter%2C+Sandra+Romai","amp;tr":["udp%3A%2F%2Ftracker.openbittorrent.com%3A80","udp%3A%2F%2Fopen.demonii.com%3A1337","udp%3A%2F%2Ftracker.coppersurfer.tk%3A6969","udp%3A%2F%2Fexodus.desync.com%3A6969"],"infoHash":"4ae89c8e7b26096110f25adffdbe6a05ac396ae3","infoHashBuffer":{"type":"Buffer","data":[74,232,156,142,123,38,9,97,16,242,90,223,253,190,106,5,172,57,106,227]},"announce":[],"urlList":[]}}