{"title":"Inked - October 2012","uid":7666494,"size":23273534,"categoryP":"other","categoryS":"e_books","magnet":"?xt=urn:btih:4e11db451550407dea210d7b27ee4cdc57036117&amp;dn=Inked+-+October+2012&amp;tr=udp%3A%2F%2Ftracker.openbittorrent.com%3A80&amp;tr=udp%3A%2F%2Fopen.demonii.com%3A1337&amp;tr=udp%3A%2F%2Ftracker.coppersurfer.tk%3A6969&amp;tr=udp%3A%2F%2Fexodus.desync.com%3A6969","seeders":1,"leechers":1,"uploader":"bpfine","files":4,"time":1348459446,"description":"\nInked - October 2012\n\n120 Pages | HQ PDF | English | 22 MB","torrent":{"xt":"urn:btih:4e11db451550407dea210d7b27ee4cdc57036117","amp;dn":"Inked+-+October+2012","amp;tr":["udp%3A%2F%2Ftracker.openbittorrent.com%3A80","udp%3A%2F%2Fopen.demonii.com%3A1337","udp%3A%2F%2Ftracker.coppersurfer.tk%3A6969","udp%3A%2F%2Fexodus.desync.com%3A6969"],"infoHash":"4e11db451550407dea210d7b27ee4cdc57036117","infoHashBuffer":{"type":"Buffer","data":[78,17,219,69,21,80,64,125,234,33,13,123,39,238,76,220,87,3,97,23]},"announce":[],"urlList":[]}}