{"title":"Top.Gear.US.S03E08.REAL.HDTV.x264-KILLERS","uid":8111934,"size":449363968,"categoryP":"video","categoryS":"tv_shows","magnet":"?xt=urn:btih:5c272a4133b4fe48ce81048236e36a4c9dd39f6c&amp;dn=Top.Gear.US.S03E08.REAL.HDTV.x264-KILLERS&amp;tr=udp%3A%2F%2Ftracker.openbittorrent.com%3A80&amp;tr=udp%3A%2F%2Fopen.demonii.com%3A1337&amp;tr=udp%3A%2F%2Ftracker.coppersurfer.tk%3A6969&amp;tr=udp%3A%2F%2Fexodus.desync.com%3A6969","seeders":1,"leechers":0,"uploader":"maximersk","files":1,"time":1360208968,"description":"Top.Gear.US.S03E08.REAL.HDTV.x264-KILLERS","torrent":{"xt":"urn:btih:5c272a4133b4fe48ce81048236e36a4c9dd39f6c","amp;dn":"Top.Gear.US.S03E08.REAL.HDTV.x264-KILLERS","amp;tr":["udp%3A%2F%2Ftracker.openbittorrent.com%3A80","udp%3A%2F%2Fopen.demonii.com%3A1337","udp%3A%2F%2Ftracker.coppersurfer.tk%3A6969","udp%3A%2F%2Fexodus.desync.com%3A6969"],"infoHash":"5c272a4133b4fe48ce81048236e36a4c9dd39f6c","infoHashBuffer":{"type":"Buffer","data":[92,39,42,65,51,180,254,72,206,129,4,130,54,227,106,76,157,211,159,108]},"announce":[],"urlList":[]}}