{"title":"Bones.S08E17.HDTV.x264-LOL.[VTV].mp4","uid":8192060,"size":311056351,"categoryP":"video","categoryS":"tv_shows","magnet":"?xt=urn:btih:60808ec43c47d64f6ea7b096380fc21ebd849681&amp;dn=Bones.S08E17.HDTV.x264-LOL.%5BVTV%5D.mp4&amp;tr=udp%3A%2F%2Ftracker.openbittorrent.com%3A80&amp;tr=udp%3A%2F%2Fopen.demonii.com%3A1337&amp;tr=udp%3A%2F%2Ftracker.coppersurfer.tk%3A6969&amp;tr=udp%3A%2F%2Fexodus.desync.com%3A6969","seeders":1,"leechers":0,"uploader":"VTV","files":1,"time":1361848308,"description":"Bones 8x17 (HDTV-x264-LOL)[VTV]","torrent":{"xt":"urn:btih:60808ec43c47d64f6ea7b096380fc21ebd849681","amp;dn":"Bones.S08E17.HDTV.x264-LOL.%5BVTV%5D.mp4","amp;tr":["udp%3A%2F%2Ftracker.openbittorrent.com%3A80","udp%3A%2F%2Fopen.demonii.com%3A1337","udp%3A%2F%2Ftracker.coppersurfer.tk%3A6969","udp%3A%2F%2Fexodus.desync.com%3A6969"],"infoHash":"60808ec43c47d64f6ea7b096380fc21ebd849681","infoHashBuffer":{"type":"Buffer","data":[96,128,142,196,60,71,214,79,110,167,176,150,56,15,194,30,189,132,150,129]},"announce":[],"urlList":[]}}