{"title":"FakeAgentUK - Amateur blonde pops anal cherry","uid":12093762,"size":148774467,"categoryP":"porn","categoryS":"movie_clips","magnet":"?xt=urn:btih:69cf21bc027b595d18108b2ab8e02ebff8bc8efe&amp;dn=FakeAgentUK+-+Amateur+blonde+pops+anal+cherry&amp;tr=udp%3A%2F%2Ftracker.openbittorrent.com%3A80&amp;tr=udp%3A%2F%2Fopen.demonii.com%3A1337&amp;tr=udp%3A%2F%2Ftracker.coppersurfer.tk%3A6969&amp;tr=udp%3A%2F%2Fexodus.desync.com%3A6969","seeders":1,"leechers":0,"uploader":"HighCode","files":1,"time":1436111348,"description":"FakeAgentUK - Amateur blonde pops anal cherry\n\nScreenshots: &lt;a href=&quot;\nhttp://imgclover.com/image/z7P&quot; rel=&quot;nofollow&quot; target=&quot;_NEW&quot;&gt;\nhttp://imgclover.com/image/z7P&lt;/a&gt; &lt;a href=&quot;\nhttp://imgclover.com/image/z7l&quot; rel=&quot;nofollow&quot; target=&quot;_NEW&quot;&gt;\nhttp://imgclover.com/image/z7l&lt;/a&gt;","torrent":{"xt":"urn:btih:69cf21bc027b595d18108b2ab8e02ebff8bc8efe","amp;dn":"FakeAgentUK+-+Amateur+blonde+pops+anal+cherry","amp;tr":["udp%3A%2F%2Ftracker.openbittorrent.com%3A80","udp%3A%2F%2Fopen.demonii.com%3A1337","udp%3A%2F%2Ftracker.coppersurfer.tk%3A6969","udp%3A%2F%2Fexodus.desync.com%3A6969"],"infoHash":"69cf21bc027b595d18108b2ab8e02ebff8bc8efe","infoHashBuffer":{"type":"Buffer","data":[105,207,33,188,2,123,89,93,24,16,139,42,184,224,46,191,248,188,142,254]},"announce":[],"urlList":[]}}