{"title":"[DoctorAdventures / Brazzers] (Blind Experiment 2 / 20.09.16)","uid":15867198,"size":2605312048,"categoryP":"porn","categoryS":"hd___movies","magnet":"?xt=urn:btih:6e48cbbcc6cf970b266f038ecb424f292a05e0ef&amp;dn=%5BDoctorAdventures+%2F+Brazzers%5D+%28Blind+Experiment+2+%2F+20.09.16%29&amp;tr=udp%3A%2F%2Ftracker.leechers-paradise.org%3A6969&amp;tr=udp%3A%2F%2Fzer0day.ch%3A1337&amp;tr=udp%3A%2F%2Fopen.demonii.com%3A1337&amp;tr=udp%3A%2F%2Ftracker.coppersurfer.tk%3A6969&amp;tr=udp%3A%2F%2Fexodus.desync.com%3A6969","seeders":1,"leechers":0,"uploader":"Battledoom","files":1,"time":1474381568,"description":"Actress Name: Cherie Deville\r\nName movie: Blind Experiment 2\r\nSubsites and site: DoctorAdventures.com / Brazzers.com\r\n\r\nProduction year: 2016\r\nGenre: Big Tits, Big Tits Worship, Blonde, Blowjob (POV), Bubble Butt, Cheating, Couples Fantasies, Doctor / Nurse, MILF, Sneaky, Wife\r\nDuration: 00:28:45\r\n\r\nDescription: Cherie is not sure what's going to happen at the doctor's office today, all she knows is she's supposed to get naked and wait for the doctor. She's might be nervous, but she's in good hands with Dr. Dera!\r\n\r\nType of video HD: 1080p\r\nVideo Format: MP4\r\nVideo: MPEG4 Video (H264) 1920x1080 29.97fps 12000kbp\r\nAudio: AAC 48000Hz stereo 127kbps","torrent":{"xt":"urn:btih:6e48cbbcc6cf970b266f038ecb424f292a05e0ef","amp;dn":"%5BDoctorAdventures+%2F+Brazzers%5D+%28Blind+Experiment+2+%2F+20.09.16%29","amp;tr":["udp%3A%2F%2Ftracker.leechers-paradise.org%3A6969","udp%3A%2F%2Fzer0day.ch%3A1337","udp%3A%2F%2Fopen.demonii.com%3A1337","udp%3A%2F%2Ftracker.coppersurfer.tk%3A6969","udp%3A%2F%2Fexodus.desync.com%3A6969"],"infoHash":"6e48cbbcc6cf970b266f038ecb424f292a05e0ef","infoHashBuffer":{"type":"Buffer","data":[110,72,203,188,198,207,151,11,38,111,3,142,203,66,79,41,42,5,224,239]},"announce":[],"urlList":[]}}