{"title":"BabyGotBoobs - Bethany Benz (My Sister is a Prude, But I'm Not!","uid":6112577,"size":320024634,"categoryP":"porn","categoryS":"movies","magnet":"?xt=urn:btih:75143e1b37764eb9cf089549fb5aec8d1b428b53&amp;dn=BabyGotBoobs+-+Bethany+Benz+%28My+Sister+is+a+Prude%2C+But+I%5C%27m+Not%21&amp;tr=udp%3A%2F%2Ftracker.openbittorrent.com%3A80&amp;tr=udp%3A%2F%2Fopen.demonii.com%3A1337&amp;tr=udp%3A%2F%2Ftracker.coppersurfer.tk%3A6969&amp;tr=udp%3A%2F%2Fexodus.desync.com%3A6969","seeders":1,"leechers":0,"uploader":"kelvin09","files":1,"time":1295417825,"description":" &lt;a href=&quot;http://www.seedimage.com/show.php/3385_2.jpg.html&quot; rel=&quot;nofollow&quot; target=&quot;_NEW&quot;&gt;http://www.seedimage.com/show.php/3385_2.jpg.html&lt;/a&gt;\n\n\nBethany is a slut. Her sister is a prude. So, when Bethany finds out her sister is not planning on fucking Keiran after their date, she devises a plan. When Keiran arrives, Bethany tells her sister that Keiran is dressed up really nice and is taking her to a 5-star restaurant. Bethany knows this will give her enough time to get exactly what she wants out of Keiran.","torrent":{"xt":"urn:btih:75143e1b37764eb9cf089549fb5aec8d1b428b53","amp;dn":"BabyGotBoobs+-+Bethany+Benz+%28My+Sister+is+a+Prude%2C+But+I%5C%27m+Not%21","amp;tr":["udp%3A%2F%2Ftracker.openbittorrent.com%3A80","udp%3A%2F%2Fopen.demonii.com%3A1337","udp%3A%2F%2Ftracker.coppersurfer.tk%3A6969","udp%3A%2F%2Fexodus.desync.com%3A6969"],"infoHash":"75143e1b37764eb9cf089549fb5aec8d1b428b53","infoHashBuffer":{"type":"Buffer","data":[117,20,62,27,55,118,78,185,207,8,149,73,251,90,236,141,27,66,139,83]},"announce":[],"urlList":[]}}