{"title":"O.Homem.Que.Sabia.Demais (1934) (legendado)","uid":7053116,"size":325725775,"categoryP":"video","categoryS":"movies","magnet":"?xt=urn:btih:753a24491562cf0769e02b1603ef51af338a9e71&amp;dn=O.Homem.Que.Sabia.Demais+%281934%29+%28legendado%29&amp;tr=udp%3A%2F%2Ftracker.openbittorrent.com%3A80&amp;tr=udp%3A%2F%2Fopen.demonii.com%3A1337&amp;tr=udp%3A%2F%2Ftracker.coppersurfer.tk%3A6969&amp;tr=udp%3A%2F%2Fexodus.desync.com%3A6969","seeders":1,"leechers":0,"uploader":"TiagoTheFlug","files":4,"time":1330014544,"description":"O Homem Que Sabia Demais (1934)\nThe Man Who Knew Too Much (original title)\nAPPROVED  75 min  -  Crime | Mystery | Thriller \nFormato: Rmvb, legenda em portuguÃƒÂªs embutida\nFonte","torrent":{"xt":"urn:btih:753a24491562cf0769e02b1603ef51af338a9e71","amp;dn":"O.Homem.Que.Sabia.Demais+%281934%29+%28legendado%29","amp;tr":["udp%3A%2F%2Ftracker.openbittorrent.com%3A80","udp%3A%2F%2Fopen.demonii.com%3A1337","udp%3A%2F%2Ftracker.coppersurfer.tk%3A6969","udp%3A%2F%2Fexodus.desync.com%3A6969"],"infoHash":"753a24491562cf0769e02b1603ef51af338a9e71","infoHashBuffer":{"type":"Buffer","data":[117,58,36,73,21,98,207,7,105,224,43,22,3,239,81,175,51,138,158,113]},"announce":[],"urlList":[]}}