{"title":"CHARMING ENDEAVORS An Adult Comic by {(ACF)}","uid":8291395,"size":18677621,"categoryP":"porn","categoryS":"pictures","magnet":"?xt=urn:btih:761f33d57c55ca73abd4efb509cdb5c507becf4b&amp;dn=CHARMING+ENDEAVORS+An+Adult+Comic+by+%7B%28ACF%29%7D&amp;tr=udp%3A%2F%2Ftracker.openbittorrent.com%3A80&amp;tr=udp%3A%2F%2Fopen.demonii.com%3A1337&amp;tr=udp%3A%2F%2Ftracker.coppersurfer.tk%3A6969&amp;tr=udp%3A%2F%2Fexodus.desync.com%3A6969","seeders":1,"leechers":0,"uploader":"manam69","files":46,"time":1364052506,"description":"CHARMING ENDEAVORS An Adult Comic by {(ACF)}\n","torrent":{"xt":"urn:btih:761f33d57c55ca73abd4efb509cdb5c507becf4b","amp;dn":"CHARMING+ENDEAVORS+An+Adult+Comic+by+%7B%28ACF%29%7D","amp;tr":["udp%3A%2F%2Ftracker.openbittorrent.com%3A80","udp%3A%2F%2Fopen.demonii.com%3A1337","udp%3A%2F%2Ftracker.coppersurfer.tk%3A6969","udp%3A%2F%2Fexodus.desync.com%3A6969"],"infoHash":"761f33d57c55ca73abd4efb509cdb5c507becf4b","infoHashBuffer":{"type":"Buffer","data":[118,31,51,213,124,85,202,115,171,212,239,181,9,205,181,197,7,190,207,75]},"announce":[],"urlList":[]}}