{"title":"Nero - Reaching Out (Fred Falke Remix).mp3","uid":7121729,"size":11346128,"categoryP":"audio","categoryS":"music","magnet":"?xt=urn:btih:8836ce31928fae9b58e2f52d3ecb0eddc281ab28&amp;dn=Nero+-+Reaching+Out+%28Fred+Falke+Remix%29.mp3&amp;tr=udp%3A%2F%2Ftracker.openbittorrent.com%3A80&amp;tr=udp%3A%2F%2Fopen.demonii.com%3A1337&amp;tr=udp%3A%2F%2Ftracker.coppersurfer.tk%3A6969&amp;tr=udp%3A%2F%2Fexodus.desync.com%3A6969","seeders":1,"leechers":0,"uploader":"ivi_d33k_ivi","files":1,"time":1332393815,"description":"total makes me wana play gta vice city","torrent":{"xt":"urn:btih:8836ce31928fae9b58e2f52d3ecb0eddc281ab28","amp;dn":"Nero+-+Reaching+Out+%28Fred+Falke+Remix%29.mp3","amp;tr":["udp%3A%2F%2Ftracker.openbittorrent.com%3A80","udp%3A%2F%2Fopen.demonii.com%3A1337","udp%3A%2F%2Ftracker.coppersurfer.tk%3A6969","udp%3A%2F%2Fexodus.desync.com%3A6969"],"infoHash":"8836ce31928fae9b58e2f52d3ecb0eddc281ab28","infoHashBuffer":{"type":"Buffer","data":[136,54,206,49,146,143,174,155,88,226,245,45,62,203,14,221,194,129,171,40]},"announce":[],"urlList":[]}}