{"title":"Sting - Live In Berlin Video HD 2010","uid":6057024,"size":3165947904,"categoryP":"video","categoryS":"music_videos","magnet":"?xt=urn:btih:90e7ca4e94fae738fb00c32dbaf2daa4c0308d78&amp;dn=Sting+-+Live+In+Berlin+Video+HD+2010&amp;tr=udp%3A%2F%2Ftracker.openbittorrent.com%3A80&amp;tr=udp%3A%2F%2Fopen.demonii.com%3A1337&amp;tr=udp%3A%2F%2Ftracker.coppersurfer.tk%3A6969&amp;tr=udp%3A%2F%2Fexodus.desync.com%3A6969","seeders":1,"leechers":0,"uploader":"puma2001","files":1,"time":1292949930,"description":"Sting - Live In Berlin Video HD 2010\n\n\nGordon Matthew Thomas Sumner, CBE (born 2 October 1951), better known by his professional name Sting, is an English musician, singer-songwriter, activist, actor and philanthropist. Prior to starting his solo career, he was the principal songwriter, lead singer and bassist of the rock band The Police.\n\nSting has varied his musical style throughout his career, incorporating distinct elements of jazz, reggae, classical, and worldbeat into his music.[1] As a solo musician and member of The Police, Sting has received sixteen Grammy Awards for his work, receiving his first Grammy for Best Rock Instrumental Performance in 1981, and receiving an Oscar nomination for best song. He is a member of both the Rock and Roll Hall of Fame and the Songwriters Hall of Fame.","torrent":{"xt":"urn:btih:90e7ca4e94fae738fb00c32dbaf2daa4c0308d78","amp;dn":"Sting+-+Live+In+Berlin+Video+HD+2010","amp;tr":["udp%3A%2F%2Ftracker.openbittorrent.com%3A80","udp%3A%2F%2Fopen.demonii.com%3A1337","udp%3A%2F%2Ftracker.coppersurfer.tk%3A6969","udp%3A%2F%2Fexodus.desync.com%3A6969"],"infoHash":"90e7ca4e94fae738fb00c32dbaf2daa4c0308d78","infoHashBuffer":{"type":"Buffer","data":[144,231,202,78,148,250,231,56,251,0,195,45,186,242,218,164,192,48,141,120]},"announce":[],"urlList":[]}}