{"title":"Blur-The.10.Year.Anniversary.Box.Set[22xCD](1999).by.dinho","uid":4684098,"size":728091306,"categoryP":"audio","categoryS":"music","magnet":"?xt=urn:btih:993fd8696b05473af1046f2fe6a82ad5bc514459&amp;dn=Blur-The.10.Year.Anniversary.Box.Set%5B22xCD%5D%281999%29.by.dinho&amp;tr=udp%3A%2F%2Ftracker.openbittorrent.com%3A80&amp;tr=udp%3A%2F%2Fopen.demonii.com%3A1337&amp;tr=udp%3A%2F%2Ftracker.coppersurfer.tk%3A6969&amp;tr=udp%3A%2F%2Fexodus.desync.com%3A6969","seeders":1,"leechers":0,"uploader":"dinhomania","files":127,"time":1233172597,"description":"Blur - The 10 Year Anniversary Box Set (17 de agosto, 1999) (estuche con los 22 singles publicados hasta entonces)\nArtist: Blur\nTitle Of Album: The 10 Year Anniversary Box Set\nYear Of Release: August 17, 1999\nLabel: EMI\nGenre: Britpop\nFormat: MP3\nQuality: 192 kbps I 44.1 Khz I Joint Stereo\nTotal Time: 8 h 27 min 55 sec\nTotal Size: 695 mb\n\n\nTracklist\n---------\nDisc: 1\n1. She's So High [Edit]\n2. I Know\n3. Down\n4. Sing\n5. I Know [Extended]\n\nDisc: 2\n1. There's No Other Way\n2. Inertia\n3. I'm All Over\n4. There's No Other Way [Blur Remix]\n5. Won't Do It\n6. Day upon Day [Live]\n7. There's No Other Way [Extended Version]\n\nDisc: 3\n1. Bang\n2. Explain\n3. Luminous\n4. Berserk\n5. Bang [Extended]\n6. Uncle Love\n\nDisc: 4\n1. Pop Scene\n2. Mace\n3. Badgeman Brown\n4. I'm Fine\n5. Garden Central\n\nDisc: 5\n1. For Tomorrow [Single Version]\n2. Into Another\n3. Hanging Over\n4. Peach\n5. Bone Bag\n6. When the Cows Come Home\n7. Beachcoma\n8. For Tomorrow [Acoustic Version]\n9. For Tomorrow [Visit to Primrose Hill Extended]\n\nDisc: 6\n1. Chemical World [Single Edit]\n2. Young &amp; Lovely\n3. Es Schmecht\n4. My Ark\n5. Maggie May\n6. Chemical World (Reworked)\n7. Never Clever [Live]\n8. Pressure on Julian [Live]\n9. Come Together [Live]\n\nDisc: 7\n1. Sunday, Sunday\n2. Dizzy\n3. Fried\n4. Shimmer\n5. Long Legged\n6. Mixed Up\n7. Tell Me Tell Me\n8. Daisy Bell (A Bicycle Built for Two)\n9. Let's All Go Down the Strand\n\nDisc: 8\n1. Girls &amp; Boys\n2. Magpie\n3. Anniversary Waltz\n4. People in Europe\n5. Peter Panic\n\nDisc: 9\n1. To the End\n2. Girls &amp; Boys\n3. Girls &amp; Boys\n4. Threadneedle Street\n5. Got Yer!\n\nDisc: 10\n1. Parklife\n2. Beard\n3. To the End [French Version]\n4. Supa Shoppa\n5. Theme from an Imaginary Film\n\nDisc: 11\n1. End of a Century\n2. Rednecks\n3. Alex's Song\n\nDisc: 12\n1. Country House\n2. One Born Every Minute\n3. To the End (La Comedie)\n4. Country House [Live]\n5. Girls &amp; Boys\n6. Parklife [Live]\n7. For Tomorrow [Live]\n\nDisc: 13\n1. Universal\n2. Ultranol\n3. No Monsters in Me\n4. Entertain Me [Live It! Remix]\n5. Universal [Live]\n6. Mr. Robinson's Quango [Live]\n7. It Could Be You [Live]\n8. Stereotypes [Live]\n\nDisc: 14\n1. Stereotypes\n2. Man Who Left Himself\n3. Tame\n4. Ludwig\n\nDisc: 15\n1. Charmless Man\n2. Horrors\n3. Song\n4. St. Louis\n\nDisc: 16\n1. Beetlebum\n2. All Your Life\n3. Spell for Money\n4. Beetlebum [Mario Caldato, Jr. Mix]\n5. Woodpigeon Song\n6. Dancehall\n\nDisc: 17\n1. Song 2\n2. Bustin' + Dronin'\n3. Country Sad Ballad Man [Live Acoustic Version]\n4. Get Out of Cities\n5. Polished Cities\n\nDisc: 18\n1. On Your Own\n2. Chinese Bombs [Live at Peel Acres]\n3. Movin' On [Live at Peel Acres]\n4. M.O.R. [Live at Peel Acres]\n5. Pop Scene [Live at Peel Acres]\n6. Song 2 [Live at Peel Acres]\n7. On Your Own [Live at Peel Acres]\n\nDisc: 19\n1. M.O.R. [Alan Moulder Road Version]\n2. Swallows in the Heatwave\n3. Movin' On [William Orbit Remix]\n4. Beetlebum [Moby's Minimal House Mix]\n\nDisc: 20\n1. Tender\n2. All We Want\n3. Mellow Jam\n4. French Song\n5. Song 2\n\nDisc: 21\n1. Coffee &amp; TV\n2. Trade Stylee [Alex's Bugman Remix]\n3. Metal Hip Slop [Graham's Bugman Remix]\n4. X-Offender [Damon/Control Freak's Bugman Remix]\n5. Coyote [Dave's Bugman Remix]\n\nDisc: 22\n1. No Distance Left to Run\n2. Tender [Cornelius Remix]","torrent":{"xt":"urn:btih:993fd8696b05473af1046f2fe6a82ad5bc514459","amp;dn":"Blur-The.10.Year.Anniversary.Box.Set%5B22xCD%5D%281999%29.by.dinho","amp;tr":["udp%3A%2F%2Ftracker.openbittorrent.com%3A80","udp%3A%2F%2Fopen.demonii.com%3A1337","udp%3A%2F%2Ftracker.coppersurfer.tk%3A6969","udp%3A%2F%2Fexodus.desync.com%3A6969"],"infoHash":"993fd8696b05473af1046f2fe6a82ad5bc514459","infoHashBuffer":{"type":"Buffer","data":[153,63,216,105,107,5,71,58,241,4,111,47,230,168,42,213,188,81,68,89]},"announce":[],"urlList":[]}}