{"title":"MLP:FiM Wallpaper Archive (version 3)","uid":6858045,"size":2590292115,"categoryP":"other","categoryS":"pictures","magnet":"?xt=urn:btih:9ffe58219734f0754c87106a7d4235b0f61b0b1b&amp;dn=MLP%3AFiM+Wallpaper+Archive+%28version+3%29&amp;tr=udp%3A%2F%2Ftracker.openbittorrent.com%3A80&amp;tr=udp%3A%2F%2Fopen.demonii.com%3A1337&amp;tr=udp%3A%2F%2Ftracker.coppersurfer.tk%3A6969&amp;tr=udp%3A%2F%2Fexodus.desync.com%3A6969","seeders":1,"leechers":0,"uploader":"ponyguin","files":1913,"time":1322775870,"description":"This torrent contains 1908 My Little Pony wallpapers. They've been compiled from various sources, such as DeviantArt and Ponychan. As time goes on, and I receive more wallpapers, I will upload updated versions of this torrent.\n\nPlease seed for as long as possible! Enjoy!\t\n\nPonychan threads and other links will be posted in the comments.\n\nQuestions, comments, concerns, etc. should be posted below.","torrent":{"xt":"urn:btih:9ffe58219734f0754c87106a7d4235b0f61b0b1b","amp;dn":"MLP%3AFiM+Wallpaper+Archive+%28version+3%29","amp;tr":["udp%3A%2F%2Ftracker.openbittorrent.com%3A80","udp%3A%2F%2Fopen.demonii.com%3A1337","udp%3A%2F%2Ftracker.coppersurfer.tk%3A6969","udp%3A%2F%2Fexodus.desync.com%3A6969"],"infoHash":"9ffe58219734f0754c87106a7d4235b0f61b0b1b","infoHashBuffer":{"type":"Buffer","data":[159,254,88,33,151,52,240,117,76,135,16,106,125,66,53,176,246,27,11,27]},"announce":[],"urlList":[]}}