{"title":"ClubDom  His Pain is Her Pleasure  720p","uid":11659836,"size":375562026,"categoryP":"porn","categoryS":"movies","magnet":"?xt=urn:btih:a2174018a9591781ced7566cfc346a099bc7b99d&amp;dn=ClubDom%5C++His+Pain+is+Her+Pleasure++720p&amp;tr=udp%3A%2F%2Ftracker.openbittorrent.com%3A80&amp;tr=udp%3A%2F%2Fopen.demonii.com%3A1337&amp;tr=udp%3A%2F%2Ftracker.coppersurfer.tk%3A6969&amp;tr=udp%3A%2F%2Fexodus.desync.com%3A6969","seeders":1,"leechers":0,"uploader":"merzedes","files":-1,"time":1417982195,"description":"ClubDom  His Pain is Her Pleasure\n\n\nScreens\n                                        &lt;a href=&quot;\nhttp://image.bayimg.com/03fc9939ce2851b0802f9b25854bbbe3af5aace0.jpg&quot; rel=&quot;nofollow&quot; target=&quot;_NEW&quot;&gt;\nhttp://image.bayimg.com/03fc9939ce2851b0802f9b25854bbbe3af5aace0.jpg&lt;/a&gt;\n\n\n16 000 Femdom/BDSM/Fetish torrentuploads completed. Man.. feels like every 1000 goes by faster and faster ;)\n\nJust keep on leaving us the nice comments below and we are happy :)\n\n\nAny Questions ?? Read our FAQ!!\n                                                          &lt;a href=&quot;\nhttp://image.bayimg.com/eaea7e9e982a9a677d61e4f5aaf93b7643bd6eeb.jpg&quot; rel=&quot;nofollow&quot; target=&quot;_NEW&quot;&gt;\nhttp://image.bayimg.com/eaea7e9e982a9a677d61e4f5aaf93b7643bd6eeb.jpg&lt;/a&gt;\n\n\nCheers  :-)","torrent":{"xt":"urn:btih:a2174018a9591781ced7566cfc346a099bc7b99d","amp;dn":"ClubDom%5C++His+Pain+is+Her+Pleasure++720p","amp;tr":["udp%3A%2F%2Ftracker.openbittorrent.com%3A80","udp%3A%2F%2Fopen.demonii.com%3A1337","udp%3A%2F%2Ftracker.coppersurfer.tk%3A6969","udp%3A%2F%2Fexodus.desync.com%3A6969"],"infoHash":"a2174018a9591781ced7566cfc346a099bc7b99d","infoHashBuffer":{"type":"Buffer","data":[162,23,64,24,169,89,23,129,206,215,86,108,252,52,106,9,155,199,185,157]},"announce":[],"urlList":[]}}