{"title":"Good Luck Charlie S02E27 Can You Keep A Secret 720p Web-DL Jaspe","uid":6895173,"size":783420649,"categoryP":"video","categoryS":"hd___tv_shows","magnet":"?xt=urn:btih:abfe40f2e272f79250dc29fef5a0db7db0dc1e50&amp;dn=Good+Luck+Charlie+S02E27+Can+You+Keep+A+Secret+720p+Web-DL+Jaspe&amp;tr=udp%3A%2F%2Ftracker.openbittorrent.com%3A80&amp;tr=udp%3A%2F%2Fopen.demonii.com%3A1337&amp;tr=udp%3A%2F%2Ftracker.coppersurfer.tk%3A6969&amp;tr=udp%3A%2F%2Fexodus.desync.com%3A6969","seeders":1,"leechers":0,"uploader":"McPay","files":-1,"time":1324166873,"description":"\nGood Luck Charlie S02 E27 Can You Keep A Secret 720p Web-DL JasperP\n\n\n\nThanks to the original Uploader!\n\n\nEnjoy!\n\n\n\n\n\nPlease seed after the download to keep it alive!!!","torrent":{"xt":"urn:btih:abfe40f2e272f79250dc29fef5a0db7db0dc1e50","amp;dn":"Good+Luck+Charlie+S02E27+Can+You+Keep+A+Secret+720p+Web-DL+Jaspe","amp;tr":["udp%3A%2F%2Ftracker.openbittorrent.com%3A80","udp%3A%2F%2Fopen.demonii.com%3A1337","udp%3A%2F%2Ftracker.coppersurfer.tk%3A6969","udp%3A%2F%2Fexodus.desync.com%3A6969"],"infoHash":"abfe40f2e272f79250dc29fef5a0db7db0dc1e50","infoHashBuffer":{"type":"Buffer","data":[171,254,64,242,226,114,247,146,80,220,41,254,245,160,219,125,176,220,30,80]},"announce":[],"urlList":[]}}