{"title":"Marvels.Agents.of.S.H.I.E.L.D.S01E01.480p.vk007.mkv","uid":8960066,"size":158284769,"categoryP":"video","categoryS":"tv_shows","magnet":"?xt=urn:btih:ac5f3a16f47cc3a6cc3d9c131dcfc0e82e5660cd&amp;dn=Marvels.Agents.of.S.H.I.E.L.D.S01E01.480p.vk007.mkv&amp;tr=udp%3A%2F%2Ftracker.openbittorrent.com%3A80&amp;tr=udp%3A%2F%2Fopen.demonii.com%3A1337&amp;tr=udp%3A%2F%2Ftracker.coppersurfer.tk%3A6969&amp;tr=udp%3A%2F%2Fexodus.desync.com%3A6969","seeders":1,"leechers":0,"uploader":"vk2340830","files":1,"time":1380083837,"description":"480p","torrent":{"xt":"urn:btih:ac5f3a16f47cc3a6cc3d9c131dcfc0e82e5660cd","amp;dn":"Marvels.Agents.of.S.H.I.E.L.D.S01E01.480p.vk007.mkv","amp;tr":["udp%3A%2F%2Ftracker.openbittorrent.com%3A80","udp%3A%2F%2Fopen.demonii.com%3A1337","udp%3A%2F%2Ftracker.coppersurfer.tk%3A6969","udp%3A%2F%2Fexodus.desync.com%3A6969"],"infoHash":"ac5f3a16f47cc3a6cc3d9c131dcfc0e82e5660cd","infoHashBuffer":{"type":"Buffer","data":[172,95,58,22,244,124,195,166,204,61,156,19,29,207,192,232,46,86,96,205]},"announce":[],"urlList":[]}}