{"title":"VA_-_Punk_Goes_Pop_6-Deluxe-Web-2015-FKK","uid":12154430,"size":114125631,"categoryP":"audio","categoryS":"music","magnet":"?xt=urn:btih:acd5b5d6ee32439e43531abe2b0caa0e063efe92&amp;dn=VA_-_Punk_Goes_Pop_6-Deluxe-Web-2015-FKK&amp;tr=udp%3A%2F%2Ftracker.openbittorrent.com%3A80&amp;tr=udp%3A%2F%2Fopen.demonii.com%3A1337&amp;tr=udp%3A%2F%2Ftracker.coppersurfer.tk%3A6969&amp;tr=udp%3A%2F%2Fexodus.desync.com%3A6969","seeders":1,"leechers":0,"uploader":"CosmicGateCZ","files":18,"time":1437736350,"description":"----- D I V i S i O N\n\nartist : VA\n\ntitle : Punk Goes Pop 6 (deluxe)\n\ngenre : Punk Rock\n\nsource : Web\n\ntype : Compilation\n\nrls date : 07.21.2015              st date : 00.00.0000\n\nsize : 108,8 MB                 tracks : 15\n\nquality : LAME 3.99 VBR             label : Fearless Records\n\nstore : http://www.amazon.de/dp/B0101BV8W6\n\nmore and different tracks compared to the retail\nenjoy\n\n/team FKK\n\n01  Tyler Carter &amp; Luke Holland - Ain't it Fun         03:48\n02  August Burns Red - Wrecking Ball                   04:13\n03  We Came as Romans - I Knew You Were Trouble        03:39\n04  Set it Off - Problem                               02:58\n05  Crown the Empire - Burn                            03:48\n06  Oceans Ate Alaska - Drunk in Love                  03:24\n07  Youth in Revolt - Royals                           03:25\n08  The Volumes - Hold On, We're Going Home            04:05\n09  Knuckle Puck - Chocolate                           03:52\n10  Slaves - Sweater Weather                           03:51\n11  State Champs - Stay the Night                      03:32\n12  The Palisades - Happy                              04:09\n13  I Prevail - Blank Space                            04:01\n14  Pvris - Chandelier                                 03:37\n15  Ice Nine Kills - Animals                           04:16\n\n56:38 min","torrent":{"xt":"urn:btih:acd5b5d6ee32439e43531abe2b0caa0e063efe92","amp;dn":"VA_-_Punk_Goes_Pop_6-Deluxe-Web-2015-FKK","amp;tr":["udp%3A%2F%2Ftracker.openbittorrent.com%3A80","udp%3A%2F%2Fopen.demonii.com%3A1337","udp%3A%2F%2Ftracker.coppersurfer.tk%3A6969","udp%3A%2F%2Fexodus.desync.com%3A6969"],"infoHash":"acd5b5d6ee32439e43531abe2b0caa0e063efe92","infoHashBuffer":{"type":"Buffer","data":[172,213,181,214,238,50,67,158,67,83,26,190,43,12,170,14,6,62,254,146]},"announce":[],"urlList":[]}}