{"title":"Shoot Em Up 2007 BluRay 720p DTS x264-3Li","uid":8250691,"size":3470896421,"categoryP":"video","categoryS":"hd___movies","magnet":"?xt=urn:btih:c261a9d78cc66f45802bb57f1347a47fcf57fcfd&amp;dn=Shoot+Em+Up+2007+BluRay+720p+DTS+x264-3Li&amp;tr=udp%3A%2F%2Ftracker.openbittorrent.com%3A80&amp;tr=udp%3A%2F%2Fopen.demonii.com%3A1337&amp;tr=udp%3A%2F%2Ftracker.coppersurfer.tk%3A6969&amp;tr=udp%3A%2F%2Fexodus.desync.com%3A6969","seeders":1,"leechers":1,"uploader":"3Li","files":-1,"time":1363161717,"description":"*Encoded/Released By.......: 3Li\n*Title/Year/Language.......: Shoot Em Up/2007/English\n*Genre.....................: Action,Comedy,Crime,Thriller \n*Subtitles External(SubRip): English,Danish,Dutch,Portuguese.\n*Subtitles External(SubRip): Romanian,Swedish,Norwegian.\n*Encoded/Profile/Level.....: 2 pass/High/Level 4.1\n*Codec/Writing Library.....: MPEG-4 AVC/H264/x264\n*Container.................: Mkv\n*Duration..................: 1h 26mn 32sec\n*Resolution................: 1280x544 pixels\n*File Size.................: 3.20 GB\n*Bit Rate..................: 4544 Kbps\n*Scan Type.................: Progressive\n*Bits/(Pixel*Frame)........: 0.272\n*Aspect Ratio/Frame Rate...: 2.35:1/23.976 fps\n*Stream Video Size.........: 2.74 GB (86%)\n*Stream Audio Size.........: 467 MB (14%)\n*Audio/Bit Rate/Language...: DTS/755 Kbps/English\n*Bit Depth.................: 24 bits\n*Channel(s)/Sampling Rate..: 6 channels/48.0 KHz\n*Channel Positions.........: Front: L C R, Side: L R, LFE\n*Chapters..................: Yes,Named\n*Sample Video Runtime/Size.: 26sec/23.3 MB\n*Source/File Size..........: Remux 1080p VC-1 DTS-HD MA 7.1-decibeL = 18.8 GB\n*Note: Make sure is a Real 3Li Release at ExtraTorrent\n*Thanks: ExtraTorrent,SaM,decibeL...","torrent":{"xt":"urn:btih:c261a9d78cc66f45802bb57f1347a47fcf57fcfd","amp;dn":"Shoot+Em+Up+2007+BluRay+720p+DTS+x264-3Li","amp;tr":["udp%3A%2F%2Ftracker.openbittorrent.com%3A80","udp%3A%2F%2Fopen.demonii.com%3A1337","udp%3A%2F%2Ftracker.coppersurfer.tk%3A6969","udp%3A%2F%2Fexodus.desync.com%3A6969"],"infoHash":"c261a9d78cc66f45802bb57f1347a47fcf57fcfd","infoHashBuffer":{"type":"Buffer","data":[194,97,169,215,140,198,111,69,128,43,181,127,19,71,164,127,207,87,252,253]},"announce":[],"urlList":[]}}