{"title":"FakeAgent - Katy - Beautiful factory worker would love to be","uid":12236097,"size":716571301,"categoryP":"porn","categoryS":"movie_clips","magnet":"?xt=urn:btih:c88b7875f769f6cce013241563e999f4e185b2b5&amp;dn=FakeAgent+-+Katy+-+Beautiful+factory+worker+would+love+to+be&amp;tr=udp%3A%2F%2Ftracker.openbittorrent.com%3A80&amp;tr=udp%3A%2F%2Fopen.demonii.com%3A1337&amp;tr=udp%3A%2F%2Ftracker.coppersurfer.tk%3A6969&amp;tr=udp%3A%2F%2Fexodus.desync.com%3A6969","seeders":1,"leechers":0,"uploader":"Ctrlme","files":1,"time":1439663828,"description":"FakeAgent - Katy - Beautiful factory worker would love to be a model\n\nScreenshot(s): &lt;a href=&quot;\nhttp://imgctrl.com/image/N72&quot; rel=&quot;nofollow&quot; target=&quot;_NEW&quot;&gt;\nhttp://imgctrl.com/image/N72&lt;/a&gt;\n &lt;a href=&quot;\nhttp://imgctrl.com/image/N7M&quot; rel=&quot;nofollow&quot; target=&quot;_NEW&quot;&gt;\nhttp://imgctrl.com/image/N7M&lt;/a&gt;\n\nCategory: Amateur, Casting, POV, Hardcore\nSize: 716571301 bytes (683.38 MiB), duration: 00:32:24, avg.bitrate: 2949 kb/s\nAudio: aac, 44100 Hz, 2 channels, s16, 110 kb/s (eng)\nVideo: h264, yuv420p, 852x480, 2707 kb/s, 24.00 fpsÂ® (eng)\n\nâ˜…â˜…â˜…â˜…â˜…â˜…â˜…â˜…â˜…â˜…â˜…â˜…â˜…â˜…â˜…â˜…â˜…â˜…â˜…â˜…â˜…â˜…â˜…â˜…â˜…â˜…â˜…â˜…â˜…â˜…â˜…â˜…â˜…â˜…â˜…â˜…â˜…â˜…â˜…â˜…â˜…â˜…â˜…â˜…â˜…â˜…â˜…â˜…â˜…â˜…â˜…â˜…â˜…â˜…â˜…â˜…\n\n               If you like this torrent, please post a comment!\n            \n                            Don't forget to seed!\n\nâ˜…â˜…â˜…â˜…â˜…â˜…â˜…â˜…â˜…â˜…â˜…â˜…â˜…â˜…â˜…â˜…â˜…â˜…â˜…â˜…â˜…â˜…â˜…â˜…â˜…â˜…â˜…â˜…â˜…â˜…â˜…â˜…â˜…â˜…â˜…â˜…â˜…â˜…â˜…â˜…â˜…â˜…â˜…â˜…â˜…â˜…â˜…â˜…â˜…â˜…â˜…â˜…â˜…â˜…â˜…â˜…\n &lt;a href=&quot;\nhttps://pirates-forum.org/User-Ctrlme&quot; rel=&quot;nofollow&quot; target=&quot;_NEW&quot;&gt;\nhttps://pirates-forum.org/User-Ctrlme&lt;/a&gt;\n &lt;a href=&quot;\nhttps://thepiratebay.vg/user/Ctrlme/&quot; rel=&quot;nofollow&quot; target=&quot;_NEW&quot;&gt;\nhttps://thepiratebay.vg/user/Ctrlme/&lt;/a&gt;","torrent":{"xt":"urn:btih:c88b7875f769f6cce013241563e999f4e185b2b5","amp;dn":"FakeAgent+-+Katy+-+Beautiful+factory+worker+would+love+to+be","amp;tr":["udp%3A%2F%2Ftracker.openbittorrent.com%3A80","udp%3A%2F%2Fopen.demonii.com%3A1337","udp%3A%2F%2Ftracker.coppersurfer.tk%3A6969","udp%3A%2F%2Fexodus.desync.com%3A6969"],"infoHash":"c88b7875f769f6cce013241563e999f4e185b2b5","infoHashBuffer":{"type":"Buffer","data":[200,139,120,117,247,105,246,204,224,19,36,21,99,233,153,244,225,133,178,181]},"announce":[],"urlList":[]}}