{"title":"RealSexScandals REALTOR","uid":3987772,"size":306015304,"categoryP":"porn","categoryS":"movies","magnet":"?xt=urn:btih:de60c18f6749ccc3b1a2d922a43011702d87e122&amp;dn=RealSexScandals+REALTOR&amp;tr=udp%3A%2F%2Ftracker.openbittorrent.com%3A80&amp;tr=udp%3A%2F%2Fopen.demonii.com%3A1337&amp;tr=udp%3A%2F%2Ftracker.coppersurfer.tk%3A6969&amp;tr=udp%3A%2F%2Fexodus.desync.com%3A6969","seeders":1,"leechers":0,"uploader":"FlamingAnt","files":4,"time":1200901724,"description":"Matthew her knows his realtor wife Judy&amp;#039;s playing him, and it&amp;#039;s time to catch her in action! When he does, she better start packin&amp;#039; cuz she&amp;#039;s SO FUCKED\n\nOk in this one the people are better looking than in the others. After you get over the fact that she&amp;#039;s a bit chubby and just focus on her big tits it&amp;#039;s not bad.\nIt is a little wierd how the dudes trying to talk about buisiness while they fuck. LOL.\n\n\n\nNot the best quality porn ever, but it&amp;#039;s real and it&amp;#039;s very funny when the cheaters confronted.\n\nThis was downloaded from realsexscandals.com. For only $3.00 I got to download as many videos as I wanted in 24 hours. A great deal. If you have a disposable credit card, perhaps a prepaid which one you can get at any drug store, I encourage you to sign up and you will get download speeds of up to 5mbps bursts and always a solid speed of at least 300kbps.\n\nI have more of these complete vids, depending on how well this one is seeded and downloaded I will release the others. But if you want to download the hundreds of videos just like this it&amp;#039;s really worth signing up.\n\nJust a warning, I&amp;#039;m not the best seeder out there, so I&amp;#039;m counting on you to help me.","torrent":{"xt":"urn:btih:de60c18f6749ccc3b1a2d922a43011702d87e122","amp;dn":"RealSexScandals+REALTOR","amp;tr":["udp%3A%2F%2Ftracker.openbittorrent.com%3A80","udp%3A%2F%2Fopen.demonii.com%3A1337","udp%3A%2F%2Ftracker.coppersurfer.tk%3A6969","udp%3A%2F%2Fexodus.desync.com%3A6969"],"infoHash":"de60c18f6749ccc3b1a2d922a43011702d87e122","infoHashBuffer":{"type":"Buffer","data":[222,96,193,143,103,73,204,195,177,162,217,34,164,48,17,112,45,135,225,34]},"announce":[],"urlList":[]}}