{"title":"John Dahlback &amp; Benny Benassi - Blink Again (Original Mix) [","uid":9836093,"size":11949916,"categoryP":"audio","categoryS":"music","magnet":"?xt=urn:btih:f37c60bc1b21d32c06ec0e1d236c0ef76595c388&amp;dn=John+Dahlback+%26amp%3B+Benny+Benassi+-+Blink+Again+%28Original+Mix%29+%5B&amp;tr=udp%3A%2F%2Ftracker.openbittorrent.com%3A80&amp;tr=udp%3A%2F%2Fopen.demonii.com%3A1337&amp;tr=udp%3A%2F%2Ftracker.coppersurfer.tk%3A6969&amp;tr=udp%3A%2F%2Fexodus.desync.com%3A6969","seeders":1,"leechers":0,"uploader":"Aevon","files":-1,"time":1395914302,"description":"John Dahlback &amp; Benny Benassi - Blink Again (Original Mix) [Ultra]\n\nGeneral\n\nFormat : MPEG Audio\nFile size : 11.3 MiB\nDuration : 4mn 58s\nOverall bit rate mode : Constant\nOverall bit rate : 320 Kbps\nAlbum : Blink Again (Original Mix) - Single\nAlbum/Performer : John Dahlback &amp; Benny Benassi\nPart/Position : 1\nPart/Total : 1\nTrack name : Blink Again (Original Mix)\nTrack name/Position : 01\nTrack name/Total : 01\nGenre : Electro House \nWriting library : LAME3.99.5\nCover Art : Yes\nCover Type : image/png\nRecord Label : Ultra\n\nComment below in the comment section for any EDM songs, etc requests and I Will try to upload it.\n\nPlease Rate,Comment and SEED.\n\nIf you like this Torrent please take a second to comment Thank You in below in the comment section.\n","torrent":{"xt":"urn:btih:f37c60bc1b21d32c06ec0e1d236c0ef76595c388","amp;dn":"John+Dahlback+%26amp%3B+Benny+Benassi+-+Blink+Again+%28Original+Mix%29+%5B","amp;tr":["udp%3A%2F%2Ftracker.openbittorrent.com%3A80","udp%3A%2F%2Fopen.demonii.com%3A1337","udp%3A%2F%2Ftracker.coppersurfer.tk%3A6969","udp%3A%2F%2Fexodus.desync.com%3A6969"],"infoHash":"f37c60bc1b21d32c06ec0e1d236c0ef76595c388","infoHashBuffer":{"type":"Buffer","data":[243,124,96,188,27,33,211,44,6,236,14,29,35,108,14,247,101,149,195,136]},"announce":[],"urlList":[]}}